caosdb/__init__.py
caosdb/apiutils.py
caosdb/cached.py
caosdb/configuration.py
caosdb/exceptions.py
caosdb/high_level_api.py
caosdb/yamlapi.py
caosdb/common/__init__.py
caosdb/common/administration.py
caosdb/common/datatype.py
caosdb/common/models.py
caosdb/common/state.py
caosdb/common/timezone.py
caosdb/common/utils.py
caosdb/common/versioning.py
caosdb/connection/__init__.py
caosdb/connection/connection.py
caosdb/connection/encode.py
caosdb/connection/interface.py
caosdb/connection/mockup.py
caosdb/connection/utils.py
caosdb/connection/authentication/__init__.py
caosdb/connection/authentication/auth_token.py
caosdb/connection/authentication/external_credentials_provider.py
caosdb/connection/authentication/input.py
caosdb/connection/authentication/interface.py
caosdb/connection/authentication/keyring.py
caosdb/connection/authentication/pass.py
caosdb/connection/authentication/plain.py
caosdb/connection/authentication/unauthenticated.py
caosdb/utils/__init__.py
caosdb/utils/caosdb_admin.py
caosdb/utils/checkFileSystemConsistency.py
caosdb/utils/create_revision.py
caosdb/utils/escape.py
caosdb/utils/get_entity.py
caosdb/utils/git_utils.py
caosdb/utils/linkahead_admin.py
caosdb/utils/plantuml.py
caosdb/utils/register_tests.py
caosdb/utils/server_side_scripting.py
linkahead/__init__.py
linkahead/apiutils.py
linkahead/cached.py
linkahead/configuration.py
linkahead/exceptions.py
linkahead/high_level_api.py
linkahead/py.typed
linkahead/schema-pycaosdb-ini.yml
linkahead/version.py
linkahead/yamlapi.py
linkahead/common/__init__.py
linkahead/common/administration.py
linkahead/common/datatype.py
linkahead/common/models.py
linkahead/common/state.py
linkahead/common/timezone.py
linkahead/common/utils.py
linkahead/common/versioning.py
linkahead/connection/__init__.py
linkahead/connection/connection.py
linkahead/connection/encode.py
linkahead/connection/interface.py
linkahead/connection/mockup.py
linkahead/connection/utils.py
linkahead/connection/authentication/__init__.py
linkahead-0.19.0.dist-info/LICENSE.md
linkahead-0.19.0.dist-info/METADATA
linkahead-0.19.0.dist-info/WHEEL
linkahead-0.19.0.dist-info/entry_points.txt
linkahead-0.19.0.dist-info/top_level.txt
linkahead-0.19.0.dist-info/RECORD
