Metadata-Version: 2.1
Name: linkahead
Version: 0.19.0
Summary: Python Interface for LinkAhead
Home-page: https://www.linkahead.org
Author: Timm Fitschen
Author-email: t.fitschen@indiscale.com
License: AGPLv3+
Classifier: Programming Language :: Python :: 3
Classifier: License :: OSI Approved :: GNU Affero General Public License v3 or later (AGPLv3+)
Classifier: Operating System :: OS Independent
Classifier: Topic :: Database
Classifier: Topic :: Scientific/Engineering :: Information Analysis
Requires-Python: >=3.9
License-File: LICENSE.md
Requires-Dist: lxml >=4.6.3
Requires-Dist: requests[socks] >=2.26
Requires-Dist: python-dateutil >=2.8.2
Requires-Dist: PyYAML >=5.4.1
Requires-Dist: future
Provides-Extra: jsonschema
Requires-Dist: jsonschema >=4.4.0 ; extra == 'jsonschema'
Provides-Extra: keyring
Requires-Dist: keyring >=13.0.0 ; extra == 'keyring'
Provides-Extra: mypy
Requires-Dist: mypy ; extra == 'mypy'
Requires-Dist: types-PyYAML ; extra == 'mypy'
Requires-Dist: types-jsonschema ; extra == 'mypy'
Requires-Dist: types-requests ; extra == 'mypy'
Requires-Dist: types-setuptools ; extra == 'mypy'
Requires-Dist: types-lxml ; extra == 'mypy'
Requires-Dist: types-python-dateutil ; extra == 'mypy'
Provides-Extra: test
Requires-Dist: pytest ; extra == 'test'
Requires-Dist: pytest-cov ; extra == 'test'
Requires-Dist: coverage >=4.4.2 ; extra == 'test'
Requires-Dist: jsonschema >=4.4.0 ; extra == 'test'
